pygwin/__init__.py
pygwin/animation.py
pygwin/box.py
pygwin/button.py
pygwin/checkbox.py
pygwin/cursor.py
pygwin/draw.py
pygwin/empty.py
pygwin/event_manager.py
pygwin/frame.py
pygwin/gauge.py
pygwin/grid.py
pygwin/horizontal_rule.py
pygwin/image.py
pygwin/input_text.py
pygwin/int_select.py
pygwin/item_select.py
pygwin/keys.py
pygwin/label.py
pygwin/mdata.py
pygwin/media.py
pygwin/menu.py
pygwin/min_max.py
pygwin/node.py
pygwin/node_type.py
pygwin/panel.py
pygwin/pos.py
pygwin/radiobox.py
pygwin/radiobox_group.py
pygwin/range.py
pygwin/rule.py
pygwin/runtime_checked_dict.py
pygwin/select.py
pygwin/style.py
pygwin/style_class.py
pygwin/subscriptable_type.py
pygwin/table.py
pygwin/test_test.py
pygwin/text_board.py
pygwin/types.py
pygwin/util.py
pygwin/valued_node.py
pygwin/vertical_rule.py
pygwin/window.py
pygwin/window_system.py
pygwin/animations/__init__.py
pygwin/animations/animation_sequence.py
pygwin/animations/fade.py
pygwin/animations/fill.py
pygwin/animations/glow.py
pygwin/animations/grow.py
pygwin/animations/node_animation.py
pygwin/animations/scroll.py
pygwin/animations/sleep_animation.py
pygwin/data/default-style.json
pygwin/data/fonts.json
pygwin/data/media/ltinternet.ttf
pygwin/data/media/window-cross.png
pygwin/test/__init__.py
pygwin/test/absolute_positioning.py
pygwin/test/all.py
pygwin/test/animations.py
pygwin/test/basic.py
pygwin/test/contextual_menus.py
pygwin/test/contextual_styles.py
pygwin/test/controls.py
pygwin/test/cursor.py
pygwin/test/fonts.py
pygwin/test/frames.py
pygwin/test/glob.py
pygwin/test/grids.py
pygwin/test/keyboard_ui.py
pygwin/test/main.py
pygwin/test/maximised.py
pygwin/test/maximised_menu.py
pygwin/test/menus.py
pygwin/test/sounds.py
pygwin/test/tables.py
pygwin/test/test.py
pygwin/test/text_boards.py
pygwin/test/tooltips.py
pygwin/test/user_controls.py
pygwin/test/data/style.json
pygwin/test/data/media/axe.png
pygwin/test/data/media/bebasneue.ttf
pygwin/test/data/media/button-base.png
pygwin-0.3.0.dist-info/LICENSE
pygwin-0.3.0.dist-info/METADATA
pygwin-0.3.0.dist-info/WHEEL
pygwin-0.3.0.dist-info/top_level.txt
pygwin-0.3.0.dist-info/RECORD
