Metadata-Version: 2.1
Name: pygwin
Version: 0.3.0
Summary: pygame window system
Home-page: https://gitlab.com/qouify/pygwin/
License: UNKNOWN
Platform: UNKNOWN
Classifier: Programming Language :: Python
Classifier: Operating System :: OS Independent
Classifier: License :: OSI Approved :: GNU General Public License v3 (GPLv3)
Requires-Python: >=3.9
License-File: LICENSE
Requires-Dist: pygame (>=2.0.0)
